rewrite_for_file/AnalyzingDataSliceWin.py
rewrite_for_file/SaveResultsWin.py
rewrite_for_file/SettingsWin.py
rewrite_for_file/analyzing_data_slice_win_design.py
rewrite_for_file/global_data.py
rewrite_for_file/main.py
rewrite_for_file/save_results_win_design.py
rewrite_for_file/settings_win_design.py
rewrite_for_file/test.vlt
rewrite_for_file-0.1.0.dist-info/METADATA
rewrite_for_file-0.1.0.dist-info/WHEEL
rewrite_for_file-0.1.0.dist-info/RECORD
