Metadata-Version: 2.1
Name: rewrite-for-file
Version: 0.1.0
Summary: 
Author: Urmasa
Author-email: n.goltsev@g.nsu.ru
Requires-Python: >=3.11,<4.0
Classifier: Programming Language :: Python :: 3
Classifier: Programming Language :: Python :: 3.11
Requires-Dist: PyQt5 (>=5.15.9,<6.0.0)
Requires-Dist: numpy (>=1.25.0,<2.0.0)
Requires-Dist: opencv-python-headless (>=4.7.0.72,<5.0.0.0)
Requires-Dist: plotly (>=5.15.0,<6.0.0)
